sp_mpsp_divadmin/__init__.py
sp_mpsp_divadmin/paths.py
sp_mpsp_divadmin/data/output/geo/sp_mpsp.7z
sp_mpsp_divadmin/data/output/geo/sp_mpsp_ar.7z
sp_mpsp_divadmin/data/output/geo/sp_mpsp_gaeco.7z
sp_mpsp_divadmin/data/output/geo/sp_mpsp_gaema.7z
sp_mpsp_divadmin/data/output/geo/sp_mpsp_macrorregioes.7z
sp_mpsp_divadmin/data/output/geo/sp_mpsp_pjreg.7z
sp_mpsp_divadmin/data/output/geo/sp_mpsp_rp.7z
sp_mpsp_divadmin/data/output/tabs/tab_gaemas_rps.csv
sp_mpsp_divadmin/data/output/tabs/tab_municipio_ar.csv
sp_mpsp_divadmin/data/output/tabs/tab_municipio_gaeco.csv
sp_mpsp_divadmin/data/output/tabs/tab_municipio_gaema.csv
sp_mpsp_divadmin/data/output/tabs/tab_municipio_macrorregioes.csv
sp_mpsp_divadmin/data/output/tabs/tab_municipio_pjreg.csv
sp_mpsp_divadmin/data/output/tabs/tab_municipio_rp.csv
sp_mpsp_divadmin-0.0.5.dist-info/LICENSE
sp_mpsp_divadmin-0.0.5.dist-info/METADATA
sp_mpsp_divadmin-0.0.5.dist-info/WHEEL
sp_mpsp_divadmin-0.0.5.dist-info/top_level.txt
sp_mpsp_divadmin-0.0.5.dist-info/RECORD
