Metadata-Version: 2.1
Name: sp-mpsp-divadmin
Version: 0.0.5
Summary: Divisão Administrativa das Áreas Regionais, GAEMAs, Redes Protetivas e Macroregiões e outras
Home-page: https://github.com/open-geodata/sp_mpsp_divadmin
Author: Michel Metran
Author-email: michelmetran@gmail.com
Keywords: python,dados espaciais,geoprocessamento
Classifier: Programming Language :: Python :: 3
Classifier: License :: OSI Approved :: MIT License
Classifier: Operating System :: OS Independent
Classifier: Natural Language :: Portuguese
Classifier: Intended Audience :: Developers
Requires-Python: >=3
License-File: LICENSE
Requires-Dist: folium
Requires-Dist: geopandas
Requires-Dist: pandas
Requires-Dist: open-geodata
